epcy/__init__.py
epcy/__main__.py
epcy/epcy.py
epcy/argparser/__init__.py
epcy/argparser/common.py
epcy/argparser/ct.py
epcy/argparser/explore.py
epcy/argparser/get_bandwidth_part.py
epcy/argparser/get_bootstrap_part.py
epcy/argparser/get_common_pred.py
epcy/argparser/get_common_profile.py
epcy/argparser/get_design_part.py
epcy/argparser/get_filter_part.py
epcy/argparser/get_gene_part.py
epcy/argparser/get_kallisto_part.py
epcy/argparser/get_log_part.py
epcy/argparser/get_matrix_part.py
epcy/argparser/get_output_part.py
epcy/argparser/get_rna_norm_part.py
epcy/argparser/kal2mat.py
epcy/argparser/pred.py
epcy/argparser/pred_rna.py
epcy/argparser/profile.py
epcy/argparser/profile_rna.py
epcy/argparser/qc.py
epcy/tests/__init__.py
epcy/tests/test.py
epcy/tools/__init__.py
epcy/tools/ct.py
epcy/tools/explore.py
epcy/tools/kal2mat.py
epcy/tools/pred.py
epcy/tools/pred_rna.py
epcy/tools/profile.py
epcy/tools/profile_rna.py
epcy/tools/qc.py
epcy/utils/Classifier.py
epcy/utils/__init__.py
epcy/utils/other.py
epcy/utils/plot.py
epcy/utils/readers.py
epcy-0.2.6.4.dist-info/LICENSE
epcy-0.2.6.4.dist-info/METADATA
epcy-0.2.6.4.dist-info/WHEEL
epcy-0.2.6.4.dist-info/entry_points.txt
epcy-0.2.6.4.dist-info/top_level.txt
epcy-0.2.6.4.dist-info/RECORD
