Metadata-Version: 2.1
Name: epcy
Version: 0.2.6.4
Summary: Evaluation of Predictive CapabilitY
Author-email: Eric Audemard <eric.audemard@umontreal.ca>
License: MIT License
Project-URL: Documentation, https://epcy.readthedocs.io/en/latest/
Project-URL: Repository, https://github.com/iric-soft/epcy.git
Project-URL: Issues, https://github.com/iric-soft/epcy/issues
Keywords: density,predictive,gene,feature,KDE
Classifier: Development Status :: 4 - Beta
Classifier: Intended Audience :: Science/Research
Classifier: Intended Audience :: Healthcare Industry
Classifier: Topic :: Scientific/Engineering :: Bio-Informatics
Classifier: Topic :: Software Development
Classifier: Topic :: Software Development :: Build Tools
Classifier: License :: OSI Approved :: MIT License
Classifier: Programming Language :: Python :: 3.11
Classifier: Natural Language :: English
Requires-Python: >=3.11
License-File: LICENSE
Requires-Dist: cython >=3.0.9
Requires-Dist: numpy >=1.26.4
Requires-Dist: pandas >=2.2.1
Requires-Dist: h5py >=3.10.0
Requires-Dist: scipy >=1.12.0
Requires-Dist: scikit-learn >=1.4.1
Requires-Dist: matplotlib >=3.8.3
Requires-Dist: numexpr >=2.9.0
Requires-Dist: seaborn >=0.13.2
